blendr/__init__.py
blendr/cli.py
blendr/ai/__init__.py
blendr/ai/data/cache.py
blendr/ai/data/data_loader.py
blendr/ai/models/__init__.py
blendr/ai/tasks/__init__.py
blendr/ai/tasks/fine_tune.py
blendr/ai/training/__init__.py
blendr/ai/training/trainer.py
blendr/auth/__init__.py
blendr/auth/authenticate.py
blendr/config/__init__.py
blendr/config/settings.py
blendr/config/setup.py
blendr/gpu_manager/__init__.py
blendr/gpu_manager/detect.py
blendr/initiate_socket/__init__.py
blendr/initiate_socket/initiate.py
blendr/lend/__init__.py
blendr/lend/setup.py
blendr/task_manager/__init__.py
blendr/task_manager/listen.py
blendrnetwork_test_cli-0.0.2.dist-info/LICENSE
blendrnetwork_test_cli-0.0.2.dist-info/METADATA
blendrnetwork_test_cli-0.0.2.dist-info/WHEEL
blendrnetwork_test_cli-0.0.2.dist-info/entry_points.txt
blendrnetwork_test_cli-0.0.2.dist-info/top_level.txt
blendrnetwork_test_cli-0.0.2.dist-info/RECORD
